MANIFEST.in
README.txt
setup.cfg
setup.py
docs/HISTORY.txt
docs/INSTALL.txt
docs/LICENSE.GPL
docs/LICENSE.txt
redomino/__init__.py
redomino/__init__.pyc
redomino.tabsandslides.egg-info/PKG-INFO
redomino.tabsandslides.egg-info/SOURCES.txt
redomino.tabsandslides.egg-info/dependency_links.txt
redomino.tabsandslides.egg-info/entry_points.txt
redomino.tabsandslides.egg-info/namespace_packages.txt
redomino.tabsandslides.egg-info/not-zip-safe
redomino.tabsandslides.egg-info/requires.txt
redomino.tabsandslides.egg-info/top_level.txt
redomino/tabsandslides/__init__.py
redomino/tabsandslides/configure.zcml
redomino/tabsandslides/i18n.sh
redomino/tabsandslides/utility.py
redomino/tabsandslides/browser/__init__.py
redomino/tabsandslides/browser/adapters.zcml
redomino/tabsandslides/browser/collection.zcml
redomino/tabsandslides/browser/common.py
redomino/tabsandslides/browser/configure.zcml
redomino/tabsandslides/browser/createobject.py
redomino/tabsandslides/browser/resources.zcml
redomino/tabsandslides/browser/adapters/gallery_adapter.pt
redomino/tabsandslides/browser/adapters/gallerypane_adapter.pt
redomino/tabsandslides/browser/adapters/imagetab_adapter.pt
redomino/tabsandslides/browser/adapters/tab_adapter.pt
redomino/tabsandslides/browser/resources/config.js
redomino/tabsandslides/browser/resources/folder.png
redomino/tabsandslides/browser/resources/jcarousel-skin.css
redomino/tabsandslides/browser/resources/jquery.easing.js
redomino/tabsandslides/browser/resources/jquery.jcarousel.js
redomino/tabsandslides/browser/resources/navigator.png
redomino/tabsandslides/browser/resources/next.png
redomino/tabsandslides/browser/resources/page.png
redomino/tabsandslides/browser/resources/prev.png
redomino/tabsandslides/browser/resources/tabs.slideshow.min.js
redomino/tabsandslides/browser/resources/tabs_and_slide_setup.js
redomino/tabsandslides/browser/resources/tabs_slideshow.css
redomino/tabsandslides/browser/resources/talexp_help.js
redomino/tabsandslides/browser/templates/accordion.pt
redomino/tabsandslides/browser/templates/gallery_folder.pt
redomino/tabsandslides/browser/templates/images_tabbed_folder.pt
redomino/tabsandslides/browser/templates/images_tabbed_folder2.pt
redomino/tabsandslides/browser/templates/slideshow_folder.pt
redomino/tabsandslides/browser/templates/tabbed_folder.pt
