Metadata-Version: 1.0
Name: redomino.tabsandslides
Version: 0.9.9
Summary: jquerytools tabs and slide implementations
Home-page: http://pypi.python.org/pypi/redomino.tabsandslides
Author: Maurizio Lupo
Author-email: maurizio.lupo@redomino.com
License: GPL
Keywords: Zope Plone Views
Platform: UNKNOWN
Classifier: Framework :: Plone
Classifier: Programming Language :: Python
Classifier: License :: OSI Approved :: GNU General Public License (GPL)
